Metadata-Version: 2.1
Name: createPackage
Version: 1.0
Summary: package to create file structure when making your own package.
Home-page: https://github.com/Sreekiranar/createPackage.git
Author-email: sreekiranar@gmail.com
License: MIT
Platform: UNKNOWN
